[
  {
    "content": "Fetch authoritative Gemma 4 specs from HF + Google docs",
    "status": "completed"
  },
  {
    "content": "Confirm scope with user (adapter mode + GGUF-only)",
    "status": "completed"
  },
  {
    "content": "Rewrite notebook against Gemma 4 architecture (35 layers, AutoModelForMultimodalLM, native chat template)",
    "status": "completed"
  },
  {
    "content": "Add runtime module discovery (§3b) to replace hard-coded Gemma 3n module list",
    "status": "completed"
  },
  {
    "content": "Collapse to single Q4_K_M target for 2-3 GB on-device footprint",
    "status": "completed"
  },
  {
    "content": "Strip LiteRT path, keep GGUF only",
    "status": "completed"
  },
  {
    "content": "Update chat_summary with Phase Z6 pivot notes",
    "status": "completed"
  }
]